{
  "generated": "2026-07-03T22:07:13+00:00",
  "data_start": "2012-09-03",
  "data_end": "2026-06-29",
  "n_obs": 722,
  "method": "PDL(degree=2)",
  "n_lags": 8,
  "r2": 0.81123,
  "rmse": 0.26962,
  "mae": 0.21383,
  "alpha": 1.139522,
  "betas": [
    0.324221,
    0.284763,
    0.239942,
    0.18976,
    0.134215,
    0.073307,
    0.007037,
    -0.064595,
    -0.14159
  ],
  "cumulative_passthrough": [
    0.3242,
    0.609,
    0.8489,
    1.0387,
    1.1729,
    1.2462,
    1.2532,
    1.1887,
    1.0471
  ],
  "total_passthrough": 1.0471,
  "seasonal_premium": 0.1872,
  "asymmetry_test": {
    "coeff": 2.254658,
    "t_stat": 6.823,
    "p_approx": 0.0,
    "significant": true
  },
  "nardl": true,
  "nardl_r2": 0.93118,
  "nardl_rmse": 0.16279,
  "nardl_data_start": "2012-09-03",
  "nardl_data_end": "2026-06-29",
  "nardl_n_obs": 722,
  "alpha_nardl": 3.238904,
  "betas_pos": [
    0.41078,
    0.482358,
    0.18572,
    0.115145,
    0.11808,
    0.04422,
    0.045285,
    0.043723,
    -0.38469
  ],
  "betas_neg": [
    0.097189,
    0.36351,
    0.165888,
    0.073682,
    0.080159,
    0.12145,
    0.018504,
    -0.080676,
    0.189664
  ],
  "total_passthrough_pos": 1.0606,
  "total_passthrough_neg": 1.0294,
  "band_passthrough": 1.0606,
  "seasonal_premium_nardl": 0.1659,
  "wald_test": {
    "sum_pos": 1.0606,
    "sum_neg": 1.0294,
    "W_stat": 831.555,
    "p_approx": 0.0,
    "significant": true
  },
  "note": "alpha/betas: symmetric PDL/OLS model (backward compat). alpha_nardl/betas_pos/betas_neg: NARDL asymmetric model (Shin-Yu-Greenwood-Nimmo 2014). band_passthrough = max(total_passthrough_pos, |total_passthrough_neg|) used by JS for pump band width. seasonal_premium added Apr-Sep; seasonal_premium_nardl from NARDL residuals."
}